Workbook

Sheet Dashboard
B2: ROTH IRA PORTFOLIO TRACKER
B3: Wealth Management Recruiting — Investment Portfolio
B5: Total Invested ($) | D5: Current Value ($) | F5: Total Return ($) | G5: Total Return (%)
B6: =Holdings!I22 -> 1575 | D6: =Holdings!J22 -> 0 | F6: =Holdings!K22 -> 0 | G6: =Holdings!L22 -> 0
B8: TARGET ALLOCATION
B9: Sleeve | C9: Target % | D9: Target $ | E9: Actual $ | F9: Actual % | G9: Δ vs Target
B10: Core (ETFs) | C10: 0.6 | D10: =C10*D6 -> 0 | E10: =Holdings!J25 -> 0 | F10: =IF(D6=0,0,E10/D6) -> 0 | G10: =E10-C10 -> -0.6
B11: Satellite (Stocks) | C11: 0.4 | D11: =C11*D6 -> 0 | E11: =Holdings!J26 -> 0 | F11: =IF(D6=0,0,E11/D6) -> 0 | G11: =E11-C11 -> -0.4
B12: TOTAL | C12: 1 | D12: =SUM(C10:C11) -> 1 | E12: =SUM(E10:E11) -> 0 | F12: =IF(D6=0,0,SUM(F10:F11)) -> 0
B14: WM INTERVIEW TALKING POINTS
B15: My investment philosophy: | C15: Long-term, diversified core with selective satellite positions where I have high conviction.
B16: Why a Roth IRA? | C16: Tax-free compounding — maximize after-tax returns over a 40+ year horizon while I'm in a low tax bracket.
B17: Core rationale: | C17: Broad market exposure via low-cost ETF captures equity risk premium; minimizes timing/selection risk.
B18: Satellite rationale: | C18: 2-3 high-conviction names with documented thesis; forces rigorous analysis and accountability.
B19: Risk management: | C19: Position sizing (no satellite >20% of portfolio), thesis review quarterly, stop-loss discipline.
B22: Last Updated: | E22: =TODAY() -> 46203

Sheet Holdings
B2: HOLDINGS — ROTH IRA
B4: Ticker | C4: Name | D4: Sleeve | E4: Shares | F4: Entry Price | G4: Current Price | H4: Cost Basis ($) | I4: Mkt Value ($) | J4: $ Return | K4: % Return | L4: % of Portfolio | M4: Date Added
B5: VTI | C5: Vanguard Total Stock Market ETF | D5: Core | E5: 3.5 | F5: 170 | G5: 170 | H5: =E5*F5 -> 595 | I5: =E5*G5 -> 595 | J5: =I5-H5 -> 0 | K5: =IF(H5=0,"-",J5/H5) -> 0 | L5: =IF(I$22=0,"-",I5/I$22) -> 0.37777778 | M5: 2026-07-01
B6: VOO | C6: Vanguard S&P 500 ETF | D6: Core | E6: 1 | F6: 480 | G6: 480 | H6: =E6*F6 -> 480 | I6: =E6*G6 -> 480 | J6: =I6-H6 -> 0 | K6: =IF(H6=0,"-",J6/H6) -> 0 | L6: =IF(I$22=0,"-",I6/I$22) -> 0.3047619 | M6: 2026-07-01
B7: [TICK] | C7: [Company Name] | D7: Satellite | E7: 2 | F7: 100 | G7: 100 | H7: =E7*F7 -> 200 | I7: =E7*G7 -> 200 | J7: =I7-H7 -> 0 | K7: =IF(H7=0,"-",J7/H7) -> 0 | L7: =IF(I$22=0,"-",I7/I$22) -> 0.12698413 | M7: 2026-07-01
B8: [TICK] | C8: [Company Name] | D8: Satellite | E8: 1 | F8: 150 | G8: 150 | H8: =E8*F8 -> 150 | I8: =E8*G8 -> 150 | J8: =I8-H8 -> 0 | K8: =IF(H8=0,"-",J8/H8) -> 0 | L8: =IF(I$22=0,"-",I8/I$22) -> 0.095238095 | M8: 2026-07-01
B9: [TICK] | C9: [Company Name] | D9: Satellite | E9: 3 | F9: 50 | G9: 50 | H9: =E9*F9 -> 150 | I9: =E9*G9 -> 150 | J9: =I9-H9 -> 0 | K9: =IF(H9=0,"-",J9/H9) -> 0 | L9: =IF(I$22=0,"-",I9/I$22) -> 0.095238095 | M9: 2026-07-01
B22: TOTAL | H22: =SUM(H5:H21) -> 1575 | I22: =SUM(I5:I21) -> 1575 | J22: =SUM(J5:J21) -> 0 | K22: =IF(H22=0,"-",J22/H22) -> 0
I25: =SUMIF(D5:D21,"Core",I5:I21) -> 1075
I26: =SUMIF(D5:D21,"Satellite",I5:I21) -> 500

Sheet Investment Thesis
B2: INVESTMENT THESIS — SATELLITE POSITIONS
B4: Ticker / Name | C4: [TICKER] — [Company Name]
B5: Date Initiated | C5: [YYYY-MM-DD]
B6: Entry Price | C6: $[XX.XX]
B7: Position Size | C7: $[XXX] (~X% of portfolio)
B8: Thesis (1-2 lines) | C8: Why I own this. What's the market missing? What's my edge?
B9: Bull Case | C9: What has to be true for this to work?
B10: Bear Case / Risks | C10: What could go wrong? How do I think about it?
B11: Catalyst | C11: What event or data point will prove/disprove the thesis?
B12: Exit Criteria | C12: I will sell if: [price target hit / thesis broken / better opportunity]
B13: Sources | C13: Earnings call / 10-K / industry research / management commentary
B15: — POSITION 2 —
B16: Ticker / Name | C16: [TICKER] — [Company Name]
B17: Date Initiated | C17: [YYYY-MM-DD]
B18: Entry Price | C18: $[XX.XX]
B19: Position Size | C19: $[XXX] (~X% of portfolio)
B20: Thesis (1-2 lines) | C20: Why I own this. What's the market missing? What's my edge?
B21: Bull Case | C21: What has to be true for this to work?
B22: Bear Case / Risks | C22: What could go wrong? How do I think about it?
B23: Catalyst | C23: What event or data point will prove/disprove the thesis?
B24: Exit Criteria | C24: I will sell if: [price target hit / thesis broken / better opportunity]
B25: Sources | C25: Earnings call / 10-K / industry research / management commentary
